EE07/_init_.py
EE07/chem_api.py
EE07/cpp_engine.py
EE07/interpreter.py
EE07/setup.py
EE07/utils.py
ee07-0.1.4.dist-info/licenses/LICENSE.txt
ee07-0.1.4.dist-info/METADATA
ee07-0.1.4.dist-info/WHEEL
ee07-0.1.4.dist-info/top_level.txt
ee07-0.1.4.dist-info/RECORD
