Metadata-Version: 2.4
Name: EE07
Version: 0.1.4
Summary: EE07 (Double-E Language) for Chemical System Programming
Author: Prakritee Chakraborty
Author-email: Prakritee Chakraborty <kriti.guitar@gmail.com>
License: MIT
Requires-Python: >=3.7
License-File: LICENSE.txt
Requires-Dist: requests
Dynamic: license-file
